{
  "dataType": "CVE_RECORD",
  "dataVersion": "5.1",
  "cveMetadata": {
    "total_count": 1,
    "last_updated": "2025-03-26T22:36:01.969886",
    "severity_distribution": {
      "critical": 0,
      "high": 0,
      "medium": 1,
      "low": 0,
      "none": 0
    }
  },
  "cves": [
    {
      "id": "CVE-2025-20230",
      "publishedDate": "2025-03-26T22:24:15.510Z",
      "lastModifiedDate": "2025-03-26T22:24:15.510Z",
      "description": "In Splunk Enterprise versions below 9.4.1, 9.3.3, 9.2.5, and 9.1.8, and versions below 3.8.38 and 3.7.23 of the Splunk Secure Gateway app on Splunk Cloud Platform, a low-privileged user that does not hold the “admin“ or “power“ Splunk roles could edit and delete other user data in App Key Value Store (KVStore) collections that the Splunk Secure Gateway app created. This is due to missing access control and incorrect ownership of the data in those KVStore collections.<br><br>In the affected versions, the `nobody` user owned the data in the KVStore collections. This meant that there was no specific owner assigned to the data in those collections.",
      "severity": 4.3,
      "references": [
        {
          "url": "https://advisory.splunk.com/advisories/SVD-2025-0307",
          "type": "reference"
        }
      ],
      "affected": [
        {
          "product": "Splunk Enterprise",
          "vendor": "Splunk",
          "versions": [
            {
              "version": "9.4",
              "status": "affected",
              "versionType": "custom",
              "lessThan": "9.4.1"
            },
            {
              "version": "9.3",
              "status": "affected",
              "versionType": "custom",
              "lessThan": "9.3.3"
            },
            {
              "version": "9.2",
              "status": "affected",
              "versionType": "custom",
              "lessThan": "9.2.5"
            },
            {
              "version": "9.1",
              "status": "affected",
              "versionType": "custom",
              "lessThan": "9.1.8"
            }
          ]
        },
        {
          "product": "Splunk Secure Gateway",
          "vendor": "Splunk",
          "versions": [
            {
              "version": "3.8",
              "status": "affected",
              "versionType": "custom",
              "lessThan": "3.8.38"
            },
            {
              "version": "3.7",
              "status": "affected",
              "versionType": "custom",
              "lessThan": "3.7.23"
            }
          ]
        }
      ],
      "problemType": [
        "The software does not restrict or incorrectly restricts access to a resource from an unauthorized actor."
      ],
      "fix_suggestion": "无法生成修复建议"
    }
  ]
}